{
 "title": "جدول تحديث مركبات وموصلين و موزعين الأسبوعي فرع الدمام-2026",
 "date": "2026-06-13",
 "main": [
  {
   "empid": "100310",
   "name": "شمون مياه ادريس مياه",
   "iqama": "2253252916",
   "job": "موصل",
   "plate": "ا س م  8013",
   "model": "2023",
   "vtype": "ايسوزو لوري",
   "pallets": "8",
   "load": "3",
   "vserial": "17554020",
   "inspect": "2027-04-01",
   "license": "2027-01-10",
   "drivercard": "2027-05-08",
   "opcard": "2027-04-02",
   "notes": "لا يوجد",
   "phone": "0504125217"
  },
  {
   "empid": "100217",
   "name": "مارييل فينود",
   "iqama": "2501620039",
   "job": "موصل",
   "plate": "أ س م 8025",
   "model": "2023",
   "vtype": "ايسوزو صندوق 2023",
   "pallets": "8",
   "load": "3",
   "vserial": "968754020",
   "inspect": "2026-10-14",
   "license": "2027-01-11",
   "drivercard": "2027-05-08",
   "opcard": "2027-04-07",
   "notes": "لم يتم تجديد ",
   "phone": "0564915114"
  },
  {
   "empid": "100327",
   "name": "محمد عبدالصبور عبدالعزيز ",
   "iqama": "2283628259",
   "job": "موصل",
   "plate": "ا س م 8024",
   "model": "2023",
   "vtype": "ايسوزو لوري",
   "pallets": "8",
   "load": "3",
   "vserial": "358754020",
   "inspect": "2026-10-14",
   "license": "2027-01-11",
   "drivercard": "2027-05-08",
   "opcard": "2027-05-05",
   "notes": "لا يوجد",
   "phone": "0565369080"
  },
  {
   "empid": "100245",
   "name": "كابيل مياه",
   "iqama": "2121612820",
   "job": "موزع",
   "plate": "ا س ح  8714 ",
   "model": "2023",
   "vtype": "متسوبيشي دينا ",
   "pallets": "4",
   "load": "3",
   "vserial": "29819910",
   "inspect": "2026-09-30",
   "license": "2029-04-02",
   "drivercard": "2026-06-26",
   "opcard": "2027-05-08",
   "notes": "(تعديل مهنة ) ",
   "phone": "0567116916"
  },
  {
   "empid": "102179",
   "name": "تنفير حسين",
   "iqama": "2519784710",
   "job": "موصل",
   "plate": "ا ر ع  2234",
   "model": "2020",
   "vtype": "متسوبيشي دينا ",
   "pallets": "4",
   "load": "3",
   "vserial": "196860810",
   "inspect": "2026-06-03",
   "license": "2026-09-10",
   "drivercard": "2027-05-08",
   "opcard": "2027-05-08",
   "notes": "لايوجد",
   "phone": "0594535961"
  },
  {
   "empid": "102181",
   "name": "محمد مصلح حمادي محسن",
   "iqama": "2536883693",
   "job": "موزع",
   "plate": "ا ر و 4140",
   "model": "2023",
   "vtype": "ايسوزو لوري",
   "pallets": "8",
   "load": "3",
   "vserial": "826065910",
   "inspect": "2027-03-14",
   "license": "2028-09-24",
   "drivercard": "2027-05-05",
   "opcard": "2027-05-08",
   "notes": "لايوجد",
   "phone": "0548827398"
  },
  {
   "empid": "101238",
   "name": "علاء عبد النبي رفاعي احمد",
   "iqama": "2485516401",
   "job": "موزع",
   "plate": "ا س  8015",
   "model": "2023",
   "vtype": "ايسوزو لوري",
   "pallets": "8",
   "load": "2",
   "vserial": "698454020",
   "inspect": "1448-12-23",
   "license": "2027-01-10",
   "drivercard": "2027-05-08",
   "opcard": "2027-04-08",
   "notes": "لايوجد",
   "phone": "0535690637"
  },
  {
   "empid": "100385",
   "name": "رفيق اسان بيلات",
   "iqama": "2407663372",
   "job": "موصل",
   "plate": "ا س ق 7776  ",
   "model": "2016",
   "vtype": "متسوبيشي لوري",
   "pallets": "8",
   "load": "2",
   "vserial": "831809610",
   "inspect": "2026-12-08",
   "license": "2026-08-30",
   "drivercard": "2027-05-08",
   "opcard": "2027-05-08",
   "notes": "لايوجد",
   "phone": "0570528945"
  },
  {
   "empid": "100360",
   "name": "ابراهيم محمد ابوزيد محمد",
   "iqama": "2393652496",
   "job": "موزع",
   "plate": "أ ر ع  2233",
   "model": "2023",
   "vtype": "متسوبيشي دينا ",
   "pallets": "4",
   "load": "3",
   "vserial": "886860810",
   "inspect": "2026-07-10",
   "license": "2026-09-10",
   "drivercard": "2026-06-28",
   "opcard": "2027-05-08",
   "notes": "",
   "phone": "0541364538"
  },
  {
   "empid": "100332",
   "name": "انفير كاريماري عمير",
   "iqama": "2350147415",
   "job": "موزع",
   "plate": "ا ر و 4085 ",
   "model": "2022",
   "vtype": "ايسوزو دينا",
   "pallets": "4",
   "load": "3",
   "vserial": "211941910",
   "inspect": "2027-02-08",
   "license": "2028-04-16",
   "drivercard": "2026-09-09",
   "opcard": "2026-12-13",
   "notes": "لايوجد",
   "phone": "0571991926"
  },
  {
   "empid": "102126",
   "name": "ارجوان",
   "iqama": "2530207360",
   "job": "موزع",
   "plate": "ا س م 8033 ",
   "model": "2023",
   "vtype": "ايسوزو لوري",
   "pallets": "8",
   "load": "3",
   "vserial": "207954020",
   "inspect": "2027-04-01",
   "license": "2027-01-11",
   "drivercard": "2027-05-08",
   "opcard": "2027-04-08",
   "notes": "لا يوجد",
   "phone": "0567948210"
  },
  {
   "empid": "100828",
   "name": "اجيت راجا",
   "iqama": "2461544377",
   "job": "موزع",
   "plate": "ا ر و 4084 ",
   "model": "2022",
   "vtype": "ايسوزو دينا",
   "pallets": "4",
   "load": "3",
   "vserial": "960941910",
   "inspect": "2027-01-10",
   "license": "2028-04-16",
   "drivercard": "2027-01-13",
   "opcard": "2026-12-13",
   "notes": "لايوجد",
   "phone": "0549131428"
  },
  {
   "empid": "100522",
   "name": "سليم اختر محمد",
   "iqama": "2430898482",
   "job": "موزع",
   "plate": "ا س ح 8670",
   "model": "2023",
   "vtype": "متسوبيشي دينا ",
   "pallets": "4",
   "load": "3",
   "vserial": "379167910",
   "inspect": "2026-11-15",
   "license": "2029-02-13",
   "drivercard": "2026-10-03",
   "opcard": "2027-05-08",
   "notes": "لايوجد",
   "phone": "0581993668"
  },
  {
   "empid": "101199",
   "name": "محمد عبدالنبي رفاعي احمد",
   "iqama": "2468851676",
   "job": "موزع",
   "plate": "ا ص ق 6853",
   "model": "2024",
   "vtype": "ايسوزو دينا",
   "pallets": "4",
   "load": "3",
   "vserial": "739131120",
   "inspect": "2027-04-04",
   "license": "2027-07-24",
   "drivercard": "2026-11-06",
   "opcard": "2027-05-05",
   "notes": "لايوجد",
   "phone": "0558654476"
  },
  {
   "empid": "100330",
   "name": "اسف باث شوهل",
   "iqama": "2325599070",
   "job": "موزع",
   "plate": "ا س ح  8717",
   "model": "2023",
   "vtype": "متسوبيشي دينا ",
   "pallets": "4",
   "load": "3",
   "vserial": "949819910",
   "inspect": "2027-03-24",
   "license": "2029-04-02",
   "drivercard": "2027-01-03",
   "opcard": "2027-05-08",
   "notes": "لايوجد",
   "phone": "0571724688"
  },
  {
   "empid": "100303",
   "name": "فالق سجاد سجاد",
   "iqama": "2090207859",
   "job": "موصل",
   "plate": "ا س م 8029 ",
   "model": "2023",
   "vtype": "ايسوزو لوري",
   "pallets": "8",
   "load": "3",
   "vserial": "537954020",
   "inspect": "2027-03-31",
   "license": "2027-01-11",
   "drivercard": "2027-03-20",
   "opcard": "2027-04-02",
   "notes": "لايوجد",
   "phone": "0558453231"
  },
  {
   "empid": "102845",
   "name": "موزيد خان",
   "iqama": "2607260698",
   "job": "موصل",
   "plate": "ا س ل 8850 ",
   "model": "2016",
   "vtype": "متسوبيشي لوري",
   "pallets": "8",
   "load": "2",
   "vserial": "451809610",
   "inspect": "2026-11-12",
   "license": "2026-10-04",
   "drivercard": "2027-05-08",
   "opcard": "2027-05-08",
   "notes": "لايوجد",
   "phone": "0572901340"
  },
  {
   "empid": "102368",
   "name": "بسام علي احمد الجلال",
   "iqama": "2537417152",
   "job": "موصل",
   "plate": "ا س م 8023 ",
   "model": "2023",
   "vtype": "ايسوزو لوري",
   "pallets": "8",
   "load": "3",
   "vserial": "277754020",
   "inspect": "2026-10-15",
   "license": "2027-01-11",
   "drivercard": "2027-04-23",
   "opcard": "2027-04-07",
   "notes": "لايوجد",
   "phone": "0536735114"
  },
  {
   "empid": "101260",
   "name": "كرم ابو الهدى صادق ",
   "iqama": "2487345031",
   "job": "موزع",
   "plate": "ا ر و  4071",
   "model": "2022",
   "vtype": "ايسوزو دينا ",
   "pallets": "4",
   "load": "3",
   "vserial": "74841910",
   "inspect": "2027-01-06",
   "license": "2028-04-16",
   "drivercard": "2027-05-04",
   "opcard": "2026-12-13",
   "notes": "لايوجد",
   "phone": "0564649987"
  },
  {
   "empid": "101936",
   "name": "مران حسين مد تارو",
   "iqama": "2505074498",
   "job": "موصل",
   "plate": "ا س م 8031 ",
   "model": "2023",
   "vtype": "ايسوزو لوري",
   "pallets": "8",
   "load": "3",
   "vserial": "317954020",
   "inspect": "2027-04-02",
   "license": "2027-01-11",
   "drivercard": "2027-05-08",
   "opcard": "2027-04-08",
   "notes": "لايوجد",
   "phone": "0550920461"
  },
  {
   "empid": "100717",
   "name": "محمد عبدالحميد محمد ",
   "iqama": "2445181585",
   "job": "موزع",
   "plate": "ا س م  8035",
   "model": "2023",
   "vtype": "ايسوزو لوري",
   "pallets": "8",
   "load": "3",
   "vserial": "776954020",
   "inspect": "2027-04-06",
   "license": "2027-01-11",
   "drivercard": "2027-05-08",
   "opcard": "2027-05-05",
   "notes": "لايوجد",
   "phone": "0564701656"
  },
  {
   "empid": "100711",
   "name": "احمد عبدالصبور رشوان",
   "iqama": "2409104953",
   "job": "موصل",
   "plate": "ا س م  8021",
   "model": "2023",
   "vtype": "ايسوزو لوري",
   "pallets": "8",
   "load": "3",
   "vserial": "538754020",
   "inspect": "2026-10-26",
   "license": "2027-01-11",
   "drivercard": "2027-05-08",
   "opcard": "2027-05-05",
   "notes": "لايوجد",
   "phone": "0567428582"
  },
  {
   "empid": "101958",
   "name": "انصار الم",
   "iqama": "2512564010",
   "job": "موصل",
   "plate": "ا ر و  4139  ",
   "model": "2023",
   "vtype": "ايسوزو لوري",
   "pallets": "8",
   "load": "3",
   "vserial": "395065910",
   "inspect": "2028-10-23",
   "license": "2028-09-24",
   "drivercard": "2027-05-08",
   "opcard": "2027-05-08",
   "notes": "لايوجد",
   "phone": "0530727974"
  },
  {
   "empid": "100249",
   "name": "شندان دبينات ",
   "iqama": "2255207751",
   "job": "موصل",
   "plate": "ا ر و 4141",
   "model": "2023",
   "vtype": "ايسوزو لوري",
   "pallets": "8",
   "load": "3",
   "vserial": "186065910",
   "inspect": "2027-02-04",
   "license": "2028-09-24",
   "drivercard": "2027-05-08",
   "opcard": "2027-05-08",
   "notes": "لايوجد",
   "phone": "0502219743"
  },
  {
   "empid": "101238",
   "name": "مد سيف الاسلام",
   "iqama": "2485516401",
   "job": "موزع",
   "plate": "ا ر ع 2240 ",
   "model": "2020",
   "vtype": "متسوبيشي دينا ",
   "pallets": "4",
   "load": "3",
   "vserial": "427860810",
   "inspect": "2026-07-09",
   "license": "2026-09-10",
   "drivercard": "2026-08-05",
   "opcard": "2027-05-08",
   "notes": "لايوجد",
   "phone": "0535690637"
  },
  {
   "empid": "100237",
   "name": "شوكت علي",
   "iqama": "2317876015",
   "job": "موصل",
   "plate": "أ س ر 8873 ",
   "model": "2020",
   "vtype": "متسوبيشي دينا ",
   "pallets": "4",
   "load": "3",
   "vserial": "203480020",
   "inspect": "2026-10-01",
   "license": "2026-08-07",
   "drivercard": "2027-05-08",
   "opcard": "2027-05-08",
   "notes": "لايوجد",
   "phone": "0551575512"
  },
  {
   "empid": "100714",
   "name": "علي محمد ابوزيد محمد",
   "iqama": "2441374739",
   "job": "موصل",
   "plate": "ا ر ل  5580 ",
   "model": "2015",
   "vtype": "ايسوزو دينا",
   "pallets": "4",
   "load": "3",
   "vserial": "322761410",
   "inspect": "2026-06-03",
   "license": "2027-06-15",
   "drivercard": "2027-05-08",
   "opcard": "2027-05-08",
   "notes": "لايوجد",
   "phone": "0530658749"
  },
  {
   "empid": "100231",
   "name": "انال كومار",
   "iqama": "2255854875",
   "job": "موصل",
   "plate": "ا س ح 8715",
   "model": "2023",
   "vtype": "متسوبيشي دينا ",
   "pallets": "4",
   "load": "2",
   "vserial": "539819910",
   "inspect": "2027-02-15",
   "license": "2029-04-02",
   "drivercard": "2027-05-09",
   "opcard": "2026-05-17",
   "notes": " لم يتم تجديد بطاقة التشغيل ",
   "phone": "0570947069"
  },
  {
   "empid": "100729",
   "name": "احمد دنقل",
   "iqama": "2441375439",
   "job": "موصل",
   "plate": "ا ص ا 7810",
   "model": "2023",
   "vtype": "هينو  دينا ",
   "pallets": "4",
   "load": "3",
   "vserial": "829737020",
   "inspect": "2026-08-24",
   "license": "2027-04-22",
   "drivercard": "2026-10-18",
   "opcard": "2026-10-21",
   "notes": "لايوجد",
   "phone": "0563480939"
  },
  {
   "empid": "100574",
   "name": "محمد عبدالرحمن السيد المندوه",
   "iqama": "2441077944",
   "job": "موزع",
   "plate": "أ ص ق 6855",
   "model": "2024",
   "vtype": "ايسوزو دينا",
   "pallets": "4",
   "load": "3",
   "vserial": "761431120",
   "inspect": "2027-04-01",
   "license": "2027-07-24",
   "drivercard": "2016-06-19",
   "opcard": "2027-05-08",
   "notes": "مقيد تغير مهنه ",
   "phone": "0576559794"
  }
 ],
 "spare": [
  {
   "empid": "————",
   "name": "فحص",
   "iqama": "————",
   "job": "——",
   "plate": "ا س ق 7774",
   "model": "2016",
   "vtype": "متسوبيشي لوري ",
   "pallets": "8",
   "load": "2",
   "vserial": "178838410",
   "inspect": "2025-11-17",
   "license": "2026-09-19",
   "drivercard": "————",
   "opcard": "2026-05-17",
   "notes": " لم يتم تجديد بطاقة التشغيل (فحص دوري + صيانة جهاز التتبع)",
   "phone": "————"
  },
  {
   "empid": "————",
   "name": "فحص",
   "iqama": "————",
   "job": "——",
   "plate": "ا س ق 7821",
   "model": "2016",
   "vtype": "متسوبيشي لوري ",
   "pallets": "8",
   "load": "3",
   "vserial": "787571510",
   "inspect": "2025-12-02",
   "license": "2026-09-26",
   "drivercard": "————",
   "opcard": "2026-05-17",
   "notes": "لم يتم تجديد بطاقة التشغيل (فحص دوري- صيانة جهاز التتبع)",
   "phone": "————"
  },
  {
   "empid": "101225",
   "name": "نديم فضل سبحان",
   "iqama": "2472649249",
   "job": "موزع",
   "plate": "أ س ق 7775",
   "model": "2016",
   "vtype": "متسوبيشي لوري ",
   "pallets": "8",
   "load": "2",
   "vserial": "490809610",
   "inspect": "2026-11-22",
   "license": "2026-09-19",
   "drivercard": "",
   "opcard": "2026-05-17",
   "notes": "ورشة خارجي (لم يتم تجديد بطاقة التشغيل  صيانة جهاز التتبع)",
   "phone": "0501901731"
  },
  {
   "empid": "100837",
   "name": "سراج ثاندو عبدول",
   "iqama": "2460710367",
   "job": "موزع",
   "plate": "أ س م 8022",
   "model": "2023",
   "vtype": "ايسوزو صندوق 2023",
   "pallets": "8",
   "load": "3",
   "vserial": "978754020",
   "inspect": "لا يوجد",
   "license": "2027-01-11",
   "drivercard": "-----------",
   "opcard": "2027-04-02",
   "notes": "ورشة خارجية للتامين ( بطاقة التشغيل منتهيه وتحتاج الى فحص دوري)",
   "phone": "0571729294"
  },
  {
   "empid": "————",
   "name": "اسبير ",
   "iqama": "————",
   "job": "——",
   "plate": "ا س ق 7920",
   "model": "2016",
   "vtype": "متسوبيشي لوري ",
   "pallets": "8",
   "load": "2",
   "vserial": "621809610",
   "inspect": "1447-05-16",
   "license": "2026-08-25",
   "drivercard": "--------------",
   "opcard": "2027-05-08",
   "notes": "عطل في المكيف ",
   "phone": "---------"
  },
  {
   "empid": "102452",
   "name": "محمد يونس",
   "iqama": "2550977850",
   "job": "موصل",
   "plate": "ا ر ع 2232",
   "model": "2020",
   "vtype": "متسوبيشي دينا ",
   "pallets": "4",
   "load": "3",
   "vserial": "386860810",
   "inspect": "2026-05-22",
   "license": "2026-09-10",
   "drivercard": "",
   "opcard": "2027-05-08",
   "notes": "لايوجد",
   "phone": "0575806817"
  }
 ],
 "vacation": [],
 "summary": {
  "drivers": "32",
  "dinas": "15",
  "lorries": "15",
  "delivery": "17",
  "distributors": "14",
  "vacation": "3"
 },
 "preparedBy": "تم إعداد هذا الجدول بواسطة قسم الحركة",
 "dept": "قسم الحركة",
 "signer": "خالد بن محمد الغامدي"
}